pronexus/__init__.py
pronexus/run.py
pronexus/library/__init__.py
pronexus/library/database.py
pronexus/library/notification.py
pronexus/pipes/__init__.py
pronexus/pipes/bonanza/__init__.py
pronexus/pipes/bonanza/etl_sap_activities.py
pronexus/pipes/bonanza/etl_sap_activity_type.py
pronexus/pipes/bonanza/etl_sap_agenda.py
pronexus/pipes/bonanza/etl_sap_business_partner_customer_contact.py
pronexus/pipes/bonanza/etl_sap_business_partner_supplier_contact.py
pronexus/pipes/bonanza/etl_sap_employee.py
pronexus/pipes/bonanza/etl_sap_employee_position.py
pronexus/pipes/bonanza/etl_sap_inventory_entry.py
pronexus/pipes/bonanza/etl_sap_inventory_exit.py
pronexus/pipes/bonanza/etl_sap_invoice.py
pronexus/pipes/bonanza/etl_sap_item.py
pronexus/pipes/bonanza/etl_sap_journal_entries.py
pronexus/pipes/bonanza/etl_sap_ordem_citas.py
pronexus/pipes/bonanza/etl_sap_ordem_trabalho.py
pronexus/pipes/bonanza/etl_sap_order.py
pronexus/pipes/bonanza/etl_sap_service_calls.py
pronexus/pipes/bonanza/etl_sap_vehicles.py
pronexus/pipes/bonanza/sap_api.py
pronexus/pipes/bonanza/model/ServiceCalls.py
pronexus/pipes/bonanza/model/__init__.py
pronexus/pipes/bonanza/model/activities.py
pronexus/pipes/bonanza/model/agenda.py
pronexus/pipes/bonanza/model/business_partner_contact.py
pronexus/pipes/bonanza/model/employee.py
pronexus/pipes/bonanza/model/inventory_entries.py
pronexus/pipes/bonanza/model/inventory_exits.py
pronexus/pipes/bonanza/model/invoice.py
pronexus/pipes/bonanza/model/item.py
pronexus/pipes/bonanza/model/journal_entry.py
pronexus/pipes/bonanza/model/ordem_citas.py
pronexus/pipes/bonanza/model/ordem_trabalho.py
pronexus/pipes/bonanza/model/orders.py
pronexus/pipes/bonanza/model/sap_model.py
pronexus/pipes/bonanza/model/vehicles.py
projjetta_pipeline_nexus-1.0.5.dist-info/METADATA
projjetta_pipeline_nexus-1.0.5.dist-info/WHEEL
projjetta_pipeline_nexus-1.0.5.dist-info/top_level.txt
projjetta_pipeline_nexus-1.0.5.dist-info/RECORD
