Metadata-Version: 2.1
Name: projjetta-pipeline-nexus
Version: 1.0.5
Summary: Pipelines para integração de dados
Home-page: https://github.com/bortolottic/nexus-integration.git
Author: Projjetta - Carlos Valdir Bortolotti
Author-email: carlos@projjetta.com
Classifier: Programming Language :: Python :: 3
Classifier: License :: OSI Approved :: MIT License
Classifier: Operating System :: OS Independent
Requires-Python: >=3.12.3
Requires-Dist: asttokens==2.4.1
Requires-Dist: certifi==2024.8.30
Requires-Dist: charset-normalizer==3.3.2
Requires-Dist: colorama==0.4.6
Requires-Dist: comm==0.2.2
Requires-Dist: Cython==3.0.11
Requires-Dist: debugpy==1.8.6
Requires-Dist: decorator==5.1.1
Requires-Dist: executing==2.1.0
Requires-Dist: greenlet==3.1.1
Requires-Dist: idna==3.10
Requires-Dist: ipykernel==6.29.5
Requires-Dist: ipython==8.28.0
Requires-Dist: jedi==0.19.1
Requires-Dist: jupyter_client==8.6.3
Requires-Dist: jupyter_core==5.7.2
Requires-Dist: matplotlib-inline==0.1.7
Requires-Dist: nest-asyncio==1.6.0
Requires-Dist: packaging==24.1
Requires-Dist: parso==0.8.4
Requires-Dist: platformdirs==4.3.6
Requires-Dist: prompt_toolkit==3.0.48
Requires-Dist: psutil==6.0.0
Requires-Dist: psycopg2==2.9.9
Requires-Dist: pure_eval==0.2.3
Requires-Dist: Pygments==2.18.0
Requires-Dist: python-dateutil==2.9.0.post0
Requires-Dist: python-env==1.0.0
Requires-Dist: pyzmq==26.2.0
Requires-Dist: requests==2.32.3
Requires-Dist: setuptools==75.1.0
Requires-Dist: setuptools-cythonize==1.0.7
Requires-Dist: six==1.16.0
Requires-Dist: SQLAlchemy==2.0.35
Requires-Dist: stack-data==0.6.3
Requires-Dist: tornado==6.4.1
Requires-Dist: traitlets==5.14.3
Requires-Dist: typing_extensions==4.12.2
Requires-Dist: urllib3==2.2.3
Requires-Dist: wcwidth==0.2.13
Requires-Dist: wheel==0.44.0
